sentience/__init__.py
sentience/net/Net.py
sentience/net/__init__.py
sentience/netsupport/HiddenLayer.py
sentience/netsupport/Layer.py
sentience/netsupport/OutputLayer.py
sentience/netsupport/__init__.py
sentience/training/InputTarget.py
sentience/training/TrainingData.py
sentience/training/TrainingDataSpecification.py
sentience/training/__init__.py
sentience/training/inputtype/Categorical.py
sentience/training/inputtype/Continuous.py
sentience/training/inputtype/Image.py
sentience/training/inputtype/Input.py
sentience/training/inputtype/__init__.py
sentience/training/parser/IDXParser.py
sentience/training/parser/Parser.py
sentience/training/parser/StandardTextParser.py
sentience/training/parser/__init__.py
sentience/training/targettype/Categorical.py
sentience/training/targettype/Continuous.py
sentience/training/targettype/Target.py
sentience/training/targettype/__init__.py
Sentience_CraigR8806-0.0.19.dist-info/LICENSE
Sentience_CraigR8806-0.0.19.dist-info/METADATA
Sentience_CraigR8806-0.0.19.dist-info/WHEEL
Sentience_CraigR8806-0.0.19.dist-info/top_level.txt
Sentience_CraigR8806-0.0.19.dist-info/RECORD
